Workbook
Name Understanding_opportunities: Lists!$C$6:$C$10

Sheet User Guide
B2: LFI Quantum Readiness & Risk Radar™ | Client User Guide
B4: 1. Overview Welcome to the LFI Quantum Readiness & Risk Radar™. This diagnostic instrument is designed to quantify your organization’s exposure to quantum threats and your potential to capture commercial value. Unlike standard maturity models, this tool utilizes the LFI QRAMM Framework (Quantum Risk Assessment & Maturity Model) to benchmark your capabilities against the 2025 Industry Standard. It separates 'hype' from 'readiness' by auditing your Data Infrastructure, Workforce Maturity, and Strategic Alignment.
B6: 2. Instructions for Assessment:
B7: Step 1: Calibration
B9: a. Navigate to the Quantum Readiness Index tab.
B11: b. Ensure the Company Name, Date, and Accountable Executive fields (Rows 1–3) are correct.
B13: Step 2: The Assessment (The Audit)
B15: a. Review the 11 Capability Domains listed in the index (Rows 6–50).
B17: b. For each domain, click the cell in the Current Maturity State column (Column G).
B19: c. Select the description from the dropdown menu that best matches your organization's current reality.
B21: Note: Be honest. Selecting 'Evaluating' when you are truly 'Not Considering' will skew your Risk Radar and mask potential vulnerabilities.
B23: d. The Readiness Score (Column H) will calculate automatically based on your selection.
... B35: This assessment is the first step in the LFI Quantum Readiness Engagement. *Score < 50: Recommended immediate focus on PQC Readiness & Crypto-Inventory. *Score > 70: Recommended focus on Use Case Heatmapping and Pilot Scaling. For questions regarding specific metric definitions or to review your results with a Virtual Chief Quantum Officer (vCQO), please contact your LFI representative.

Sheet Executive Summary
B2: LFI Quantum Readiness & Risk Radar™
B4: Strategic Pillar | C4: Weighted Readiness Score (0~100)
B5: Strategy (The Why) | C5: =(AVERAGE('Quantum Readiness Index'!H6:H23) / 2.5) * 100 -> 21.111111
B6: Technology (The How) | C6: =(AVERAGE('Quantum Readiness Index'!H24:H33) / 2.5) * 100 -> 48
B7: Operations (The Who) | C7: =(AVERAGE('Quantum Readiness Index'!H34:H50) / 2.5) * 100 -> 60
B8: TOTAL QRI SCORE* | C8: =(C5 * 0.14) + (C6 * 0.29) + (C7 * 0.57) -> 51.075556
B10: Current Maturity State: | C10: =LOOKUP(C8, {0,30,50,70,85}, {"The Ostrich (Passive)","The Tourist (Evaluating)","The Pilot Trap (Experimenting)","The Scaler (Operationalizing)","The Leader (Dominating)"}) -> The Pilot Trap (Experimenting)
B15: STRATEGY
B16: A. Actionable Intelligence | C16: =(AVERAGE('Quantum Readiness Index'!H6:H10)/2.5)*100 -> 44
B17: B. Capturing Business Value | C17: =(AVERAGE('Quantum Readiness Index'!H11:H15)/2.5)*100 -> 0
B18: C. Securing IP | C18: =(AVERAGE('Quantum Readiness Index'!H16:H20)/2.5)*100 -> 12
B19: D. Regulations & Standards | C19: =(AVERAGE('Quantum Readiness Index'!H21:H23)/2.5)*100 -> 33.333333
B20: TECHNOLOGY
B21: E. Orchestration | C21: =(AVERAGE('Quantum Readiness Index'!H24:H27)/2.5)*100 -> 30
B22: F. AI/ML Models | C22: =(AVERAGE('Quantum Readiness Index'!H28:H30)/2.5)*100 -> 46.666667
B23: G. DevSecOps (App) | C23: =(AVERAGE('Quantum Readiness Index'!H31:H33)/2.5)*100 -> 73.333333
B24: OPERATIONS
B25: H. Governance | C25: =(AVERAGE('Quantum Readiness Index'!H34:H37)/2.5)*100 -> 25
B26: I. Talent Strategy | C26: =(AVERAGE('Quantum Readiness Index'!H38:H42)/2.5)*100 -> 60
B27: J. Innovation Process | C27: =(AVERAGE('Quantum Readiness Index'!H43:H46)/2.5)*100 -> 75
B28: K. High Velocity R&D | C28: =(AVERAGE('Quantum Readiness Index'!H47:H50)/2.5)*100 -> 80
B32: THREAT RADAR
B33: IP Defense (C.11) | C33: =(('Quantum Readiness Index'!H16)/2.5)*100 -> 0
B34: Trade Secret Strategy (C.12) | C34: =(('Quantum Readiness Index'!H17)/2.5)*100 -> 0
B35: PQC Compliance (D.17) | C35: =(('Quantum Readiness Index'!H22)/2.5)*100 -> 60
B36: Crypto-Agility (K.45) | C36: =(('Quantum Readiness Index'!H50)/2.5)*100 -> 80
B37: OPPORTUNITY RADAR
B38: NP-Hard Heatmap (A.1) | C38: =(('Quantum Readiness Index'!H6)/2.5)*100 -> 60
B39: Commercial Value (B.6) | C39: =(('Quantum Readiness Index'!H11)/2.5)*100 -> 0
B40: Heuristic Solvers (F.24) | C40: =(('Quantum Readiness Index'!H29)/2.5)*100 -> 60
B41: ROI Hypothesis (J.40) | C41: =(('Quantum Readiness Index'!H45)/2.5)*100 -> 60
B47: NOTES:
B48: *The LFI Standard QRI Weighting: The Total QRI Score is not a simple average. It uses a weighted formula to reflect that Organizational Readiness is the primary driver of success, not just hardware access.
B49: 1. Operations (57% Weight): The Execution Engine. This is the heaviest component because superior technology fails without the workforce, governance, and workflows to integrate it.
B50: 2. Technology (29% Weight): The Technical Foundation. Measures the maturity of your stack, including security (DevSecOps) and hybrid orchestration capabilities.
B51: 3. Strategy (14% Weight): The Vision. While critical for direction, a strategy document alone does not constitute readiness. It is the easiest pillar to complete, hence the lowest weight.
B53: Methodology: This assessment utilizes the QRAMM Framework to audit data infrastructure, identify CVI (Cryptographically Relevant) gaps, and prioritize commercial use cases.

Sheet Quantum Readiness Index
B3: Company Name: | D3: Date: | F3: Accountable Executive:
B5: Strategic Pillar | C5: Capability Domain | D5: Assessment Standard | E5: LFI Process Description | F5: Business Impact / ROI | G5: Current Maturity State | H5: Readiness Score (0~2.5)
B6: PILLAR 1: STRATEGY | C6: A. Actionable Quantum Intelligence | D6: A.1: Understanding opportunities | E6: We systematically map high-value organizational pain points to specific quantum capabilities to determine where the technology applies. | F6: We deploy the Use Case Heatmap. We audit your operational data to find the actual NP-Hard bottlenecks (e.g., job shop scheduling) ripe for quantum acceleration. | G6: 3. Experimenting / In Progress - We have a formal project underway to identify use cases. We are actively assessing specific pain points against quantum modalities. | H6: =IFERROR(CHOOSE(VALUE(LEFT(TRIM(G6),1)), 0, 1, 1.5, 2, 2.5), "") -> 1.5
D7: A.2: Forecasting market scenarios | E7: We maintain dynamic predictive models to estimate exactly when quantum advantage will disrupt our specific industry sector. | F7: We provide commercial reality checks. We tell you when the technology will impact your P&L, not when a paper is published. | G7: 4. Mostly Complete - We have a solid forecast for our key sectors. The model exists and informs strategy, but it may lack real-time updates or full executive buy-in | H7: =IFERROR(CHOOSE(VALUE(LEFT(TRIM(G7),1)), 0, 1, 1.5, 2, 2.5), "") -> 2
D8: A.3: Monitoring market data | E8: We operate a "listening post" to track competitor activity, hardware breakthroughs, and investment signals in real-time. | F8: We perform the Competitor Impact Analysis. A market-first analysis of how your competitors are deploying deep tech, arming you with the 'case for action'. | G8: 4. Mostly Complete - We have a structured monitoring process. We track key indices (investment, hardware specs, patents) and distribute regular updates to stakeholders. | H8: =IFERROR(CHOOSE(VALUE(LEFT(TRIM(G8),1)), 0, 1, 1.5, 2, 2.5), "") -> 2
D9: A.4: Business value of startups | E9: We rigorously vet the vendor landscape to distinguish viable technology partners from "PowerPoint" startups. | F9: We perform Vendor Due Diligence. We know which startups are vaporware and which have real hardware access. | G9: 1. Not Considering / Not Started - We do not assess the quantum startup landscape. We generally wait for established tech giants (e.g., IBM, Google) to provide solutions. | H9: =IFERROR(CHOOSE(VALUE(LEFT(TRIM(G9),1)), 0, 1, 1.5, 2, 2.5), "") -> 0
D10: A.5: Acquisition pipeline | E10: We identify specific targets for M&A or strategic partnerships to rapidly secure necessary talent and intellectual property. | F10: We leverage The LFI Syndicate. If you need to acquire a team to catch up, we identify the targets before they hit the open market. | G10: 1. Not Considering / Not Started - We do not view M&A as a lever for quantum readiness. We assume we will build all capabilities internally or rent them as a service. | H10: =IFERROR(CHOOSE(VALUE(LEFT(TRIM(G10),1)), 0, 1, 1.5, 2, 2.5), "") -> 0
C11: B. Capturing Quantum Business Value | D11: B.6: Use case differentiation | E11: We articulate exactly why a quantum approach offers a superior mathematical advantage over classical solvers for specific problems. | F11: We quantify the Commercial Opportunity. We separate true quantum advantage from 'hype' by proving which problems hit the Complexity Wall. | G11: 1. Not Considering / Not Started - We do not distinguish between classical and quantum use cases. We assume all our computational problems are best solved by classical HPC. | H11: =IFERROR(CHOOSE(VALUE(LEFT(TRIM(G11),1)), 0, 1, 1.5, 2, 2.5), "") -> 0
D12: B.7: Timing of value realization | E12: We maintain a financial roadmap that predicts the "break-even" date for quantum investments based on technical milestones. | F12: We build the ROI Roadmap. We align quantum milestones to your fiscal quarters to justify the OPEX. | G12: 1. Not Considering / Not Started - We have no timeline for when quantum computing will deliver value. We view it as "futuristic" R&D with an undefined horizon. | H12: =IFERROR(CHOOSE(VALUE(LEFT(TRIM(G12),1)), 0, 1, 1.5, 2, 2.5), "") -> 0
D13: B.8: Processes and governance | E13: We enforce strict decision gates to fund, continue, or kill quantum projects based on predefined performance KPIs. | F13: We hold the Kill Switch. We establish the metrics to shut down underperforming projects instantly. | G13: 1. Not Considering / Not Started - We manage quantum projects ad-hoc. There are no formal processes or specific governance structures for quantum initiatives. | H13: =IFERROR(CHOOSE(VALUE(LEFT(TRIM(G13),1)), 0, 1, 1.5, 2, 2.5), "") -> 0
D14: B.9: No-regret capabilities | E14: We invest in foundational assets, such as improved data structures, that yield ROI even if quantum hardware is delayed. | F14: We ensure every dollar spent improves your classical stack (e.g., data hygiene) even if the quantum era is delayed. | G14: 1. Not Considering / Not Started - We are only investing in quantum-specific hardware or pilots. We have not identified capabilities that serve both classical and quantum needs. | H14: =IFERROR(CHOOSE(VALUE(LEFT(TRIM(G14),1)), 0, 1, 1.5, 2, 2.5), "") -> 0
D15: B.10: Use case exploration | E15: We run experimental proofs-of-concept across diverse domains (optimization, simulation, AI) to validate feasibility before scaling. | F15: We manage a Diversified Portfolio (Optimization + Simulation) to hedge your bets against uncertainty. | G15: 1. Not Considering / Not Started - We have not explored any quantum use cases. We have no active experiments or pilots running. | H15: =IFERROR(CHOOSE(VALUE(LEFT(TRIM(G15),1)), 0, 1, 1.5, 2, 2.5), "") -> 0
C16: C. Securing Quantum IP | D16: C.11: Protection of IP | E16: We implement legal frameworks ensuring that "Foreground IP" created during vendor engagements is retained by the organization. | F16: We negotiate "Foreground IP" rights. We ensure you own the algorithm the vendor builds for you. | G16: 1. Not Considering / Not Started - We accept standard vendor terms. We have not reviewed IP ownership clauses in our cloud access or consulting contracts. | H16: =IFERROR(CHOOSE(VALUE(LEFT(TRIM(G16),1)), 0, 1, 1.5, 2, 2.5), "") -> 0
D17: C.12: Decision models | E17: We utilize a logic tree to determine whether new inventions should be patented, open-sourced, or protected as trade secrets. | F17: We provide the "Trade Secret vs. Patent" framework to protect you from the "Harvest Now, Decrypt Later" threat. | G17: 1. Not Considering / Not Started - We have no model for IP classification. We treat all innovation the same, usually by ignoring it or letting the individual researcher decide. | H17: =IFERROR(CHOOSE(VALUE(LEFT(TRIM(G17),1)), 0, 1, 1.5, 2, 2.5), "") -> 0
D18: C.13: Invention assessments | E18: We convene a technical review board to evaluate the novelty and patentability of algorithms developed by our internal teams. | F18: We audit your R&D labs to capture and catalogue "accidental" innovations. | G18: 1. Not Considering / Not Started - We have no process for capturing inventions. We rely on researchers to self-identify if they have created something valuable. | H18: =IFERROR(CHOOSE(VALUE(LEFT(TRIM(G18),1)), 0, 1, 1.5, 2, 2.5), "") -> 0
D19: C.14: New filings | E19: We actively file patents to build a defensive "IP moat" around our specific quantum applications and workflows. | F19: We drive a defensive patent strategy to block competitors from operating in your specific vertical. | G19: 3. Experimenting / In Progress - We have filed 1-2 provisional patents based on initial pilots. Filings are sporadic and driven by individual researcher initiative rather than corporate strategy. | H19: =IFERROR(CHOOSE(VALUE(LEFT(TRIM(G19),1)), 0, 1, 1.5, 2, 2.5), "") -> 1.5
D20: C.15: Licensing strategy | E20: We develop mechanisms to monetize our proprietary quantum solutions by licensing them to suppliers or partners. | F20: We turn your quantum cost center into a profit center by structuring licensing deals for your supply chain. | G20: 1. Not Considering / Not Started - We view our quantum work solely for internal use. We have no intention or mechanism to license our discoveries to third parties. | H20: =IFERROR(CHOOSE(VALUE(LEFT(TRIM(G20),1)), 0, 1, 1.5, 2, 2.5), "") -> 0
C21: D. Regulations and Standards | D21: D.16: Engaging regulatory agencies | E21: We proactively dialogue with government bodies (e.g., FDA, FAA) to define certification paths for quantum-derived results. | F21: We speak "Federal." We handle the certification conversations with bodies like the FAA or FDA. | G21: 2. Evaluating / Planning - We are monitoring regulatory news (e.g., export controls on QPU hardware). We are internalizing the guidelines but have not reached out to agencies. | H21: =IFERROR(CHOOSE(VALUE(LEFT(TRIM(G21),1)), 0, 1, 1.5, 2, 2.5), "") -> 1
D22: D.17: Understanding standards | E22: We align our protocols with emerging industry standards (e.g., IEEE, NIST) to ensure interoperability and compliance. | F22: We conduct the PQC Readiness & Crypto-Inventory. We audit your data infrastructure to identify Crypto-Agile Gaps and build your migration roadmap. | G22: 3. Experimenting / In Progress - We are conducting a "Gap Analysis." We are testing if our current pilots can be ported to a standard format (e.g., OpenQASM) or if they break. | H22: =IFERROR(CHOOSE(VALUE(LEFT(TRIM(G22),1)), 0, 1, 1.5, 2, 2.5), "") -> 1.5
D23: D.18: Stakeholder collaboration | E23: We participate in industry consortiums to shape the regulatory landscape rather than passively reacting to it. | F23: We represent your interests in consortiums (e.g., QED-C), saving your executives time. | G23: 1. Not Considering / Not Started - We operate in stealth mode or isolation. We do not engage with other players in the quantum ecosystem. | H23: =IFERROR(CHOOSE(VALUE(LEFT(TRIM(G23),1)), 0, 1, 1.5, 2, 2.5), "") -> 0
B24: PILLAR 2: TECHNOLOGY | C24: E. Quantum-Classical Orchestration | D24: E.19: Containerized workloads | E24: We isolate quantum code into portable containers to ensure consistent deployment across diverse hardware backends. | F24: We prevent Vendor Lock-in. We ensure your code is portable and not hard-coded to a single machine. | G24: 3. Experimenting / In Progress - We have containerized specific pilots. We are testing if we can package a quantum circuit and its classical pre-processing into a single deployable unit. | H24: =IFERROR(CHOOSE(VALUE(LEFT(TRIM(G24),1)), 0, 1, 1.5, 2, 2.5), "") -> 1.5
D25: E.20: Quantum-classical orchestration | E25: We automate the workflow to seamlessly hand off tasks between classical processors and quantum units without manual intervention. | F25: We deploy the "Hybrid" layer. We automate the handoff so your Classical CPU and Quantum QPU work as one unit. | G25: 3. Experimenting / In Progress - We have scripted a basic loop. A Python script sends a job to the cloud QPU, waits for the result, and processes it. Latency is high due to queue times and network lag. | H25: =IFERROR(CHOOSE(VALUE(LEFT(TRIM(G25),1)), 0, 1, 1.5, 2, 2.5), "") -> 1.5
D26: E.21: Optimized application times | E26: We engineer workflows to minimize latency and queue times when accessing cloud-based quantum processors. | F26: We reduce "Time-to-Solution." We optimize circuit depth to lower your cloud compute bills. | G26: 1. Not Considering / Not Started - We run circuits "as is" without optimization. We accept high wait times and long execution durations as the cost of doing business. | H26: =IFERROR(CHOOSE(VALUE(LEFT(TRIM(G26),1)), 0, 1, 1.5, 2, 2.5), "") -> 0
D27: E.22: Interoperating workloads | E27: We ensure quantum outputs can be directly ingested by downstream enterprise applications like ERP or logistics software. | F27: We bridge the "Valley of Death." We hook the quantum solver directly into your existing SAP/ERP systems. | G27: 1. Not Considering / Not Started - Our quantum workloads are isolated "science experiments." The data stays within the quantum team. We have no connection to enterprise IT systems. | H27: =IFERROR(CHOOSE(VALUE(LEFT(TRIM(G27),1)), 0, 1, 1.5, 2, 2.5), "") -> 0
C28: F. AI/ML Computational Models | D28: F.23: AI/ML models | E28: We leverage quantum simulation to generate synthetic training data that enhances the accuracy of your classical AI models. | F28: We execute the "AQ Convergence." We use quantum simulation to generate synthetic data to train your AI models. | G28: 1. Not Considering / Not Started - We manage AI and Quantum as completely separate silos. Our data science team has no interaction with the quantum research team. | H28: =IFERROR(CHOOSE(VALUE(LEFT(TRIM(G28),1)), 0, 1, 1.5, 2, 2.5), "") -> 0
D29: F.24: Advanced computational models | E29: We deploy hybrid solvers, such as Variational Quantum Algorithms, that combine quantum sampling with classical optimization. | F29: We bring the library of "Heuristics." We deploy pre-built solvers for logistics and chemistry so you don't start from scratch. | G29: 3. Experimenting / In Progress - We are running "Toy Models." We have replaced a small section of a classical simulation with a quantum circuit. It is currently slower and less accurate, but it proves the connection works. | H29: =IFERROR(CHOOSE(VALUE(LEFT(TRIM(G29),1)), 0, 1, 1.5, 2, 2.5), "") -> 1.5
D30: F.25: Data maturity | E30: We audit and structure our classical data to ensure it is sufficiently clean and formatted for quantum processing. | F30: We perform the "Garbage In" audit. We clean your classical data structures so they are actually ingestible by a QPU. | G30: 4. Mostly Complete - Our data is API-accessible and "Schema-Strict." We have automated pipelines that clean and normalize data specifically for high-performance computing ingestion. | H30: =IFERROR(CHOOSE(VALUE(LEFT(TRIM(G30),1)), 0, 1, 1.5, 2, 2.5), "") -> 2
C31: G. DevSecOps for Quantum Applications | D31: G.26: Cloud-based tools | E31: We secure managed access to quantum backends via aggregated platforms rather than purchasing dedicated hardware. | F31: We manage the "App Store." We provide aggregated access to multiple backends (Pasqal, QuEra, IBM) via one contract. | G31: 4. Mostly Complete - We have enterprise-grade access. We utilize "Reserved Instances" or dedicated access to ensure our jobs run without waiting in public queues. We have central billing and security controls. | H31: =IFERROR(CHOOSE(VALUE(LEFT(TRIM(G31),1)), 0, 1, 1.5, 2, 2.5), "") -> 2
D32: G.27: Continuous integration and delivery (CI/CD) | E32: We establish automated pipelines for testing, verifying, and deploying updates to quantum circuits. | F32: We professionalize the code. We move your team from "Jupyter Notebooks" to enterprise-grade software engineering. | G32: 4. Mostly Complete - We have a robust pipeline. We run regression tests against simulators and small-scale quantum hardware. We catch breaking changes in vendor SDKs automatically. | H32: =IFERROR(CHOOSE(VALUE(LEFT(TRIM(G32),1)), 0, 1, 1.5, 2, 2.5), "") -> 2
D33: G.28: Administration tools | E33: We utilize dashboards to monitor compute usage, manage costs, and control user access to quantum resources. | F33: We enforce "Cost Governance." We track every second of QPU usage to prevent budget overruns. | G33: 3. Experimenting / In Progress - We have a single administrator who manually manages access keys and tracks usage via spreadsheets. Reporting is retroactive (at the end of the month). | H33: =IFERROR(CHOOSE(VALUE(LEFT(TRIM(G33),1)), 0, 1, 1.5, 2, 2.5), "") -> 1.5
B34: PILLAR 3: OPERATIONS | C34: H. Governance of Quantum Roadmap | D34: H.29: Alignment of innovation roadmaps | E34: We synchronize quantum development milestones with the broader corporate product release cycles. | F34: We force the conversation. We ensure the quantum roadmap actually supports the product launch roadmap. | G34: 1. Not Considering / Not Started - We develop our quantum strategy independently of vendor roadmaps. We assume "the hardware will be there" when we are ready. | H34: =IFERROR(CHOOSE(VALUE(LEFT(TRIM(G34),1)), 0, 1, 1.5, 2, 2.5), "") -> 0
D35: H.30: Integration with R&D | E35: We embed quantum experts directly into core R&D product teams rather than isolating them in a separate lab. | F35: We break the silos. We embed quantum physicists into your manufacturing teams to solve real problems. | G35: 1. Not Considering / Not Started - Our quantum team operates as a completely separate unit (e.g., "Special Projects"). There is no formal interaction or shared roadmap with the main R&D division. | H35: =IFERROR(CHOOSE(VALUE(LEFT(TRIM(G35),1)), 0, 1, 1.5, 2, 2.5), "") -> 0
D36: H.31: Shared business-tech exec responsibility | E36: We ensure both technical leaders (CIO) and business unit leaders hold shared accountability for quantum KPIs. | F36: We are the "Board Advisor." We translate technical risk into business language for the C-Suite. | G36: 3. Experimenting / In Progress - We have a "Business Sponsor" for our pilots. They lend their name to the project to help secure funding, but they do not have specific deliverables. | H36: =IFERROR(CHOOSE(VALUE(LEFT(TRIM(G36),1)), 0, 1, 1.5, 2, 2.5), "") -> 1.5
D37: H.32: Centers of Excellence | E37: We formalize a central unit to consolidate best practices, standardize tools, and disseminate knowledge across the firm. | F37: We build your Internal Training Academy. We institutionalize knowledge so it doesn't leave when an employee departs the company. | G37: 2. Evaluating / Planning - We are discussing the need for a CoE. We are identifying which experts should belong to it, but currently, they sit in isolated silos (e.g., IT vs. R&D). | H37: =IFERROR(CHOOSE(VALUE(LEFT(TRIM(G37),1)), 0, 1, 1.5, 2, 2.5), "") -> 1
C38: I. Quantum Talent Strategy | D38: I.33: Budgeting | E38: We allocate a specific, ring-fenced budget for quantum initiatives that accounts for the high failure rate of R&D experiments. | F38: We act as the "Fiduciary." We structure the budget to account for high failure rates in early experiments. | G38: 3. Experimenting / In Progress - We have Project-Based funding. We got $500k for this specific pilot. If it fails, the money stops. We are terrified of taking risks because we need a win to survive. | H38: =IFERROR(CHOOSE(VALUE(LEFT(TRIM(G38),1)), 0, 1, 1.5, 2, 2.5), "") -> 1.5
D39: I.34: Staffing | E39: We build a balanced team of quantum physicists, software engineers, and "translators" who bridge the domain gap. | F39: We are the "Fractional Solution." You partner with our expertise for a fraction of the cost of hiring a full-time lead. | G39: 2. Evaluating / Planning - We are writing job descriptions. We are debating whether to hire a senior physicist or a fresh PhD. We have not made an offer yet. | H39: =IFERROR(CHOOSE(VALUE(LEFT(TRIM(G39),1)), 0, 1, 1.5, 2, 2.5), "") -> 1
D40: I.35: Community participation | E40: We encourage our technical staff to contribute to open-source libraries and publish research to attract top talent. | F40: We enhance your "Employer Brand." We help you publish non-sensitive work to attract top-tier talent. | G40: 3. Experimenting / In Progress - We allow Passive participation. Staff can attend conferences and fix minor bugs in public libraries, but they cannot release significant code or act as maintainers. | H40: =IFERROR(CHOOSE(VALUE(LEFT(TRIM(G40),1)), 0, 1, 1.5, 2, 2.5), "") -> 1.5
D41: I.36: Innovation culture | E41: We foster an environment that rewards experimental learning and does not penalize "scientific failure". | F41: We provide "Psychological Safety." We frame negative results as "learning data," not failure. | G41: 3. Experimenting / In Progress - We allow failure in The Lab. The R&D team has a safe space to fail, but they must sanitize their reports before presenting to the Board to look successful. | H41: =IFERROR(CHOOSE(VALUE(LEFT(TRIM(G41),1)), 0, 1, 1.5, 2, 2.5), "") -> 1.5
D42: I.37: Risk tolerance | E42: We explicitly define and accept the long-term, high-risk nature of quantum investments at the board level. | F42: We define the "Stop Loss." We set clear boundaries on how much risk the organization accepts | G42: 4. Mostly Complete - We have a Strategic Risk Framework. The Board has signed off on a 3-year Zero Revenue period for Quantum. We view the risk as "Asymmetric", the cost of doing nothing is higher than the cost of failing. | H42: =IFERROR(CHOOSE(VALUE(LEFT(TRIM(G42),1)), 0, 1, 1.5, 2, 2.5), "") -> 2
C43: J. Quantum Innovation Process | D43: J.38: Ideation to integration | E43: We utilize a standardized funnel process to move concepts efficiently from whiteboard theory to production reality. | F43: We install the "Funnel." A rigorous process to move ideas from whiteboard to production. | G43: 4. Mostly Complete - We have a Stage-Gate Process. We have formal review gates (Idea -> Feasibility -> Pilot -> Production). We kill bad ideas early and resource good ideas for integration. | H43: =IFERROR(CHOOSE(VALUE(LEFT(TRIM(G43),1)), 0, 1, 1.5, 2, 2.5), "") -> 2
D44: J.39: Strategic planning models | E44: We integrate quantum computing projections into our long-term (5-10 year) corporate strategy documents. | F44: We future-proof the strategy. We integrate quantum horizons into your 5-year corporate plan. | G44: 4. Mostly Complete - We use Scenario Planning. Our corporate strategy includes Quantum Accelerate and Quantum Stagnate scenarios. We have modeled how a breakthrough in 2027 would alter our supply chain and competitive positioning. | H44: =IFERROR(CHOOSE(VALUE(LEFT(TRIM(G44),1)), 0, 1, 1.5, 2, 2.5), "") -> 2
D45: J.40: Expected business value | E45: We require every project to start with a defined "Value Hypothesis" quantifying the potential operational impact. | F45: We demand the "Value Hypothesis." We don't start a project unless the projected ROI is clear. | G45: 3. Experimenting / In Progress - We calculate value after the fact. We finish a pilot and then try to back-calculate what it might be worth if scaled. We are rationalizing the spend rather than justifying the investment. | H45: =IFERROR(CHOOSE(VALUE(LEFT(TRIM(G45),1)), 0, 1, 1.5, 2, 2.5), "") -> 1.5
D46: J.41: Solution certificates | E46: We establish internal standards to certify that a quantum solution is robust enough for production deployment. | F46: We validate the output. We certify that the solution is robust enough for critical manufacturing lines. | G46: 4. Mostly Complete - We have a "Robustness Standard." To be certified for production, a solution must pass a "Noise Resilience Test." It must prove it can maintain accuracy even when error rates spike by 10%. | H46: =IFERROR(CHOOSE(VALUE(LEFT(TRIM(G46),1)), 0, 1, 1.5, 2, 2.5), "") -> 2
C47: K. High Velocity Research and Development | D47: K.42: Agile methodology | E47: We operate using iterative sprints to rapidly test and refine quantum circuits based on feedback. | F47: We drive speed. We run weekly sprints to iterate on circuit designs faster than your competition. | G47: 4. Mostly Complete - We use "Dual-Track Agile." The Software Engineering team runs standard 2-week sprints. The Physics team runs longer, variable "Research Cycles." They sync up every month to integrate. | H47: =IFERROR(CHOOSE(VALUE(LEFT(TRIM(G47),1)), 0, 1, 1.5, 2, 2.5), "") -> 2
D48: K.43: Incremental deployment | E48: We release value in staged phases, starting with hybrid heuristics, rather than waiting for perfect fault tolerance. | F48: We deliver "Efficiency Now." We focus on near-term heuristic advantages while waiting for fault tolerance. | G48: 4. Mostly Complete - We utilize "Heuristic Advantages." We deploy solutions that use quantum (or quantum-inspired) solvers to break out of local minima, even if the final optimization is classical. We capture small wins (1-2% efficiency gains). | H48: =IFERROR(CHOOSE(VALUE(LEFT(TRIM(G48),1)), 0, 1, 1.5, 2, 2.5), "") -> 2
D49: K.44: Continuous workflow enhancements | E49: We constantly update our algorithms to leverage the latest improvements in hardware fidelity and qubit counts. | F49: We keep you current. We update your algorithms to match the latest hardware specs (e.g., 100+ qubits). | G49: 4. Mostly Complete - We have Scheduled Optimization Cycles. Our CI/CD pipeline includes a Re-Transpilation step. We verify that our circuits are using the latest native gate sets (e.g., Dynamic Circuits) supported by the backend. | H49: =IFERROR(CHOOSE(VALUE(LEFT(TRIM(G49),1)), 0, 1, 1.5, 2, 2.5), "") -> 2
D50: K.45: DevSecOps (Operational) | E50: We embed security protocols, including post-quantum cryptography, directly into the development lifecycle from day one. | F50: We mitigate the "HNDL" threat. We embed Post-Quantum Cryptography into your ops layer from Day 1. | G50: 4. Mostly Complete - We have "Obfuscated Execution." We use circuit knitting or data masking techniques to ensure that the quantum cloud provider never sees the full problem. We treat the quantum backend as an "Untrusted Environment." | H50: =IFERROR(CHOOSE(VALUE(LEFT(TRIM(G50),1)), 0, 1, 1.5, 2, 2.5), "") -> 2
B51: PILLAR 4: FINANCIAL IMPACT (The "Cost") | C51: L. Efficiency Valuation | D51: L.46: Operational Bleed | E51: What is the estimated annual revenue lost to "unsolvable" operational friction (e.g., stockouts, unplanned downtime, yield loss)? | F51: We convert "operational headaches" into a hard dollar figure (The Cost of Stagnation) to justify immediate investment.
D52: L. 47: Waste & Scrap | E52: What is your current annual Scrap Rate (as a % of COGS) or "Giveaway" (over-spec production)? | F52: We identify the "invisible margin" that quantum-enabled optimization can reclaim from your production floor.
C53: M. Sovereignty Valuation | D53: M. 48: IP Valuation | E53: What is the estimated valuation of your "Crown Jewel" trade secrets (e.g., formulas, proprietary alloys, algorithms)? | F53: Value: We quantify the "Termination Event" risk: the financial impact if your core IP were decrypted by a competitor tomorrow.
D54: M. 49: Data Shelf Life | E54: How many years must this data remain secret to retain its competitive value (e.g., 5, 10, 20 years)? | F54: We determine your "Harvest Now, Decrypt Later" risk window. If Shelf Life > 5 years, you are already in the danger zone.

Sheet Calculator
C2: Table 1: The Cost of Stagnation (Efficiency Risk) | H2: Table 2: The Cost of Sovereignty (Security Risk)
C3: Use this to calculate the immediate "Money on the Table." | H3: Use this to calculate the long-term "Existential Threat."
E5: Value | K5: Value
C6: Annual Revenue | E6: 500000000 | H6: C. Intellectual Property Exposure
I7: Value of Top 5 Trade Secrets / R&D Assets | K7: 100000000
C8: A. Unmet Demand Loss
D9: Est. % Revenue Lost to Stockouts/Downtime | E9: 0.03 | I9: Data Shelf Life (Years) | K9: 15
D11: Revenue at Risk (A) | E11: =E6*E9 -> 15000000 | I11: Quantum Risk Horizon (Years to Q-Day) | K11: 5
C13: B. Production Waste | H13: HNDL Risk Status | K13: =IF(K9 > K11, "CRITICAL", "LOW") -> CRITICAL
D14: Annual Cost of Goods Sold (COGS) | E14: 350000000
H15: TOTAL SOVEREIGNTY VALUE AT RISK | K15: =K7 -> 100000000 | L15: This is the asset value exposed to immediate harvesting.
D16: Current Scrap / Yield Loss Rate (%) | E16: 0.04
D18: Cash Burned on Waste (B) | E18: =E14*E16 -> 14000000
C20: TOTAL COST OF STAGNATION (A + B) | E20: =E11+E18 -> 29000000
B24: Deliver the Verdict: "Mr. CEO, our audit shows a Readiness Score of 2.5/5, but more importantly, it identifies $29M in annual efficiency losses and $100M in IP exposure. The proposed $250k Pilot is just 0.8% of the efficiency loss you are accepting this year."

Sheet Lists
C5: ='Quantum Readiness Index'!D6 -> A.1: Understanding opportunities | F5: ='Quantum Readiness Index'!D7 -> A.2: Forecasting market scenarios | I5: ='Quantum Readiness Index'!D8 -> A.3: Monitoring market data | L5: ='Quantum Readiness Index'!D9 -> A.4: Business value of startups | O5: ='Quantum Readiness Index'!D10 -> A.5: Acquisition pipeline | R5: ='Quantum Readiness Index'!D11 -> B.6: Use case differentiation | U5: ='Quantum Readiness Index'!D12 -> B.7: Timing of value realization | X5: ='Quantum Readiness Index'!D13 -> B.8: Processes and governance | AA5: ='Quantum Readiness Index'!D14 -> B.9: No-regret capabilities | AD5: ='Quantum Readiness Index'!D15 -> B.10: Use case exploration | AG5: ='Quantum Readiness Index'!D16 -> C.11: Protection of IP | AJ5: ='Quantum Readiness Index'!D17 -> C.12: Decision models | AM5: ='Quantum Readiness Index'!D18 -> C.13: Invention assessments | AP5: ='Quantum Readiness Index'!D19 -> C.14: New filings | AS5: ='Quantum Readiness Index'!D20 -> C.15: Licensing strategy | AV5: ='Quantum Readiness Index'!D21 -> D.16: Engaging regulatory agencies | AY5: ='Quantum Readiness Index'!D22 -> D.17: Understanding standards | BB5: ='Quantum Readiness Index'!D23 -> D.18: Stakeholder collaboration | BE5: ='Quantum Readiness Index'!D24 -> E.19: Containerized workloads | BH5: ='Quantum Readiness Index'!D25 -> E.20: Quantum-classical orchestration | BK5: ='Quantum Readiness Index'!D26 -> E.21: Optimized application times | BN5: ='Quantum Readiness Index'!D27 -> E.22: Interoperating workloads | BQ5: ='Quantum Readiness Index'!D28 -> F.23: AI/ML models | BT5: ='Quantum Readiness Index'!D29 -> F.24: Advanced computational models | BW5: ='Quantum Readiness Index'!D30 -> F.25: Data maturity | BZ5: ='Quantum Readiness Index'!D31 -> G.26: Cloud-based tools | CC5: ='Quantum Readiness Index'!D32 -> G.27: Continuous integration and delivery (CI/CD) | CF5: ='Quantum Readiness Index'!D33 -> G.28: Administration tools | CI5: ='Quantum Readiness Index'!D34 -> H.29: Alignment of innovation roadmaps | CL5: ='Quantum Readiness Index'!D35 -> H.30: Integration with R&D | CO5: ='Quantum Readiness Index'!D36 -> H.31: Shared business-tech exec responsibility | CR5: ='Quantum Readiness Index'!D37 -> H.32: Centers of Excellence | CU5: ='Quantum Readiness Index'!D38 -> I.33: Budgeting | CX5: ='Quantum Readiness Index'!D39 -> I.34: Staffing | DA5: ='Quantum Readiness Index'!D40 -> I.35: Community participation | DD5: ='Quantum Readiness Index'!D41 -> I.36: Innovation culture | DG5: ='Quantum Readiness Index'!D42 -> I.37: Risk tolerance | DJ5: ='Quantum Readiness Index'!D43 -> J.38: Ideation to integration | DM5: ='Quantum Readiness Index'!D44 -> J.39: Strategic planning models | DP5: ='Quantum Readiness Index'!D45 -> J.40: Expected business value | DS5: ='Quantum Readiness Index'!D46 -> J.41: Solution certificates | DV5: ='Quantum Readiness Index'!D47 -> K.42: Agile methodology | DY5: ='Quantum Readiness Index'!D48 -> K.43: Incremental deployment | EB5: ='Quantum Readiness Index'!D49 -> K.44: Continuous workflow enhancements | EE5: ='Quantum Readiness Index'!D50 -> K.45: DevSecOps (Operational)
C6: 1. Not Considering / Not Started - We have not taken any action to identify or map potential business opportunities for quantum computing. | D6: 0 | F6: 1. Not Considering / Not Started - We do not track or forecast when quantum computing will impact our market. We react to news as it happens. | G6: 0 | I6: 1. Not Considering / Not Started - We do not actively monitor the quantum market. We have no process for tracking external developments or competitor moves. | J6: 0 | L6: 1. Not Considering / Not Started - We do not assess the quantum startup landscape. We generally wait for established tech giants (e.g., IBM, Google) to provide solutions. | M6: 0 | O6: 1. Not Considering / Not Started - We do not view M&A as a lever for quantum readiness. We assume we will build all capabilities internally or rent them as a service. | P6: 0 | R6: 1. Not Considering / Not Started - We do not distinguish between classical and quantum use cases. We assume all our computational problems are best solved by classical HPC. | S6: 0 | U6: 1. Not Considering / Not Started - We have no timeline for when quantum computing will deliver value. We view it as "futuristic" R&D with an undefined horizon. | V6: 0 | X6: 1. Not Considering / Not Started - We manage quantum projects ad-hoc. There are no formal processes or specific governance structures for quantum initiatives. | Y6: 0 | AA6: 1. Not Considering / Not Started - We are only investing in quantum-specific hardware or pilots. We have not identified capabilities that serve both classical and quantum needs. | AB6: 0 | AD6: 1. Not Considering / Not Started - We have not explored any quantum use cases. We have no active experiments or pilots running. | AE6: 0 | AG6: 1. Not Considering / Not Started - We accept standard vendor terms. We have not reviewed IP ownership clauses in our cloud access or consulting contracts. | AH6: 0 | AJ6: 1. Not Considering / Not Started - We have no model for IP classification. We treat all innovation the same, usually by ignoring it or letting the individual researcher decide. | AK6: 0 | AM6: 1. Not Considering / Not Started - We have no process for capturing inventions. We rely on researchers to self-identify if they have created something valuable. | AN6: 0 | AP6: 1. Not Considering / Not Started - We have zero quantum-specific patent filings. We rely entirely on trade secrets or assume we will license everything from vendors. | AQ6: 0 | AS6: 1. Not Considering / Not Started - We view our quantum work solely for internal use. We have no intention or mechanism to license our discoveries to third parties. | AT6: 0 | AV6: 1. Not Considering / Not Started - We have had no contact with regulators regarding quantum computing. We assume existing frameworks for classical simulation will apply automatically. | AW6: 0 | AY6: 1. Not Considering / Not Started - We pay no attention to quantum standards. We use whatever proprietary format our hardware vendor provides (e.g., vendor-specific assembly languages). | AZ6: 0 | BB6: 1. Not Considering / Not Started - We operate in stealth mode or isolation. We do not engage with other players in the quantum ecosystem. | BC6: 0 | BE6: 1. Not Considering / Not Started - Our quantum code exists as local Python scripts on individual laptops. We do not use containerization technology (e.g., Docker) for quantum workloads. | BF6: 0 | BH6: 1. Not Considering / Not Started - We run quantum jobs manually. We treat the quantum computer as a separate "lab experiment." Data is manually extracted from the QPU and loaded into classical tools. | BI6: 0 | BK6: 1. Not Considering / Not Started - We run circuits "as is" without optimization. We accept high wait times and long execution durations as the cost of doing business. | BL6: 0 | BN6: 1. Not Considering / Not Started - Our quantum workloads are isolated "science experiments." The data stays within the quantum team. We have no connection to enterprise IT systems. | BO6: 0 | BQ6: 1. Not Considering / Not Started - We manage AI and Quantum as completely separate silos. Our data science team has no interaction with the quantum research team. | BR6: 0 | BT6: 1. Not Considering / Not Started - We run standard classical models only. We have not attempted to identify which parts of our math could be offloaded to a quantum processor. | BU6: 0 | BW6: 1. Not Considering / Not Started - Our data is siloed, unstructured, and often manually managed (spreadsheets). We have no standardized data governance. | BX6: 0 | BZ6: 1. Not Considering / Not Started - We do not use cloud-based quantum tools. We rely on local simulators on laptops or have no access to quantum hardware at all. | CA6: 0 | CC6: 1. Not Considering / Not Started - We deploy quantum code manually. We do not have automated testing or deployment pipelines. Updates are ad-hoc. | CD6: 0 | CF6: 1. Not Considering / Not Started - We have no central administration. Developers create their own accounts (sometimes with personal emails) and put expenses on individual credit cards. | CG6: 0 | CI6: 1. Not Considering / Not Started - We develop our quantum strategy independently of vendor roadmaps. We assume "the hardware will be there" when we are ready. | CJ6: 0 | CL6: 1. Not Considering / Not Started - Our quantum team operates as a completely separate unit (e.g., "Special Projects"). There is no formal interaction or shared roadmap with the main R&D division. | CM6: 0 | CO6: 1. Not Considering / Not Started - Quantum is viewed entirely as an "IT Project" or "R&D Experiment." Business leaders are passive observers or unaware. | CP6: 0 | CR6: 1. Not Considering / Not Started - We have no central body. Knowledge is scattered across individual laptops and minds. If our lead quantum engineer leaves, their knowledge leaves with them. | CS6: 0 | CU6: 1. Not Considering / Not Started - We have no dedicated budget. Any quantum work is done "off the side of the desk" or uses leftover discretionary funds from other IT projects at the end of the year. | CV6: 0 | CX6: 1. Not Considering / Not Started - We have no dedicated quantum staff. We rely on "enthusiasts" from other departments who dabble in quantum during their spare time. | CY6: 0 | DA6: 1. Not Considering / Not Started - We are a "Black Box." Our employment contracts strictly forbid contributing to open source or publishing papers. We prioritize total secrecy over reputation. | DB6: 0 | DD6: 1. Not Considering / Not Started - We have a Zero Defect culture. Failure is viewed as incompetence. If a project doesn't deliver ROI, the lead is reprimanded. We prioritize execution over exploration. | DE6: 0 | DG6: 1. Not Considering / Not Started - We have a "quarter-to-quarter" mindset. If a project doesn't show ROI in 6 months, it is cancelled. We view quantum as a "moonshot" that we can't afford right now. | DH6: 0 | DJ6: 1. Not Considering / Not Started - We have Whiteboard Warriors. We have brilliant mathematical theories on the whiteboard, but no process for coding, testing, or deploying them. Ideas die in the room where they were born. | DK6: 0 | DM6: 1. Not Considering / Not Started - Quantum computing is absent from our corporate strategy documents. It is considered a niche science experiment with no projected impact on the P&L over the next decade. | DN6: 0 | DP6: 1. Not Considering / Not Started - We choose projects based on technical interest or what the vendor suggests. We have no calculations regarding business value. We are doing "science for science's sake." | DQ6: 0 | DS6: 1. Not Considering / Not Started - We have no formal certification process for quantum code. If the researcher says "it works," we deploy it. We rely entirely on trust rather than verification. | DT6: 0 | DV6: 1. Not Considering / Not Started - We work in Waterfall. We define a 6-month research goal and don't check the results until the end. We view Sprints as something only software developers do. | DW6: 0 | DY6: 1. Not Considering / Not Started - We have a Fault Tolerance or Bust mindset. We believe current (NISQ) devices are useless noise. We plan to wait until 2030+ to deploy our first solution. | DZ6: 0 | EB6: 1. Not Considering / Not Started - We practice "Write Once, Run Forever." We built a pilot two years ago and haven't touched the code since. We are running 2023 algorithms on 2025 hardware, wasting the new capabilities. | EC6: 0 | EE6: 1. Not Considering / Not Started - We have no specific security protocols for quantum. We treat quantum jobs as public research and often send data to cloud providers without encryption or anonymization. | EF6: 0
C7: 2. Evaluating / Planning - We have begun initial, ad-hoc discussions or literature reviews to understand where quantum might apply, but no formal mapping exists. | D7: 1 | F7: 2. Evaluating / Planning - We are reviewing external analyst reports (like this one) to understand general timelines, but we have no internal forecasting capability. | G7: 1 | I7: 2. Evaluating / Planning - We rely on general news feeds and occasional ad-hoc reading of public articles to stay informed, but there is no structured intake. | J7: 1 | L7: 2. Evaluating / Planning - We are aware of major startup names but evaluate them ad-hoc. We treat all vendors roughly the same without a structured due diligence framework. | M7: 1 | O7: 2. Evaluating / Planning - We have discussed "Buy vs. Build" in strategy meetings. We acknowledge that an acquisition might be necessary eventually, but have no targets. | P7: 1 | R7: 2. Evaluating / Planning - We are learning the theoretical differences. We understand concepts like "exponential speedup" in the abstract, but haven't applied them to our specific workflows. | S7: 1 | U7: 2. Evaluating / Planning - We have general expectations (e.g., "in the next decade") based on industry reports, but no specific roadmap for our own use cases. | V7: 1 | X7: 2. Evaluating / Planning - We are reviewing our existing IT governance to see if it applies to quantum. We recognize the need for specific rules but haven't written them. | Y7: 1 | AA7: 2. Evaluating / Planning - We are identifying which existing capabilities (e.g., advanced linear algebra, HPC workflows) would benefit from a quantum-focus update. | AB7: 1 | AD7: 2. Evaluating / Planning - We are researching potential use cases on paper. We are debating which problem (e.g., Portfolio Optimization vs. Risk Analysis) fits best, but haven't run code. | AE7: 1 | AG7: 2. Evaluating / Planning - Legal is reviewing our standard "Master Services Agreements" (MSAs) to see if they cover quantum-specific inventions. We know we should own it, but have no specific clauses yet. | AH7: 1 | AJ7: 2. Evaluating / Planning - We are discussing the trade-offs between patents and trade secrets. We understand that "secrecy" might be better for algorithms, but we have no formal guidelines. | AK7: 1 | AM7: 2. Evaluating / Planning - We encourage teams to share ideas, but reviews are ad-hoc. A manager might review a concept if a researcher brings it up, but there is no standard criteria. | AN7: 1 | AP7: 2. Evaluating / Planning - We are conducting "Freedom to Operate" searches. We are identifying whitespace where we could file, but have not yet submitted an application. | AQ7: 1 | AS7: 2. Evaluating / Planning - We are identifying which parts of our IP portfolio could be licensed (e.g., a specific data encoding method) versus what must remain exclusive. | AT7: 1 | AV7: 2. Evaluating / Planning - We are monitoring regulatory news (e.g., export controls on QPU hardware). We are internalizing the guidelines but have not reached out to agencies. | AW7: 1 | AY7: 2. Evaluating / Planning - We are monitoring the development of standards like NIST’s Post-Quantum Cryptography (PQC) or the Quantum Intermediate Representation (QIR). | AZ7: 1 | BB7: 2. Evaluating / Planning - We have identified relevant consortiums (e.g., QED-C, national quantum initiatives). We are debating membership fees and value but haven't joined. | BC7: 1 | BE7: 2. Evaluating / Planning - We acknowledge the need for containerization. We are reviewing how to adapt our standard DevOps practices to handle quantum libraries (e.g., Qiskit, Cirq). | BF7: 1 | BH7: 2. Evaluating / Planning - We are designing the architecture for a hybrid workflow. We are evaluating tools (e.g., Qiskit Runtime, NVIDIA CUDA-Q) that can manage the interplay. | BI7: 1 | BK7: 2. Evaluating / Planning - We are profiling our applications to find bottlenecks. We analyze how much time is spent in the queue vs. running on the chip. | BL7: 1 | BN7: 2. Evaluating / Planning - We are mapping the APIs required to connect quantum backends to our core business platforms (e.g., cloud data lakes, ERP). We know where the "plumbing" needs to go. | BO7: 1 | BQ7: 2. Evaluating / Planning - We are researching "Quantum Machine Learning" (QML) theory. We are identifying which parts of our classical AI stack (e.g., feature mapping) could benefit from a quantum kernel. | BR7: 1 | BT7: 2. Evaluating / Planning - We are profiling our current HPC workloads. We are identifying the specific mathematical kernels (e.g., matrix inversion) that are slowing us down and mapping them to quantum possibilities. | BU7: 1 | BW7: 2. Evaluating / Planning - We are cleaning our data for classical Machine Learning (ML). We are standardizing formats, but we aren't thinking about Quantum encoding requirements yet. | BX7: 1 | BZ7: 2. Evaluating / Planning - We are reviewing cloud providers. We are comparing pricing models (e.g., pay-per-shot vs. monthly subscription) and reading documentation, but have not provisioned access. | CA7: 1 | CC7: 2. Evaluating / Planning - We are reviewing how our existing DevOps tools (e.g., Jenkins, GitLab) can support quantum libraries. We are defining what a "Quantum Unit Test" should look like. | CD7: 1 | CF7: 2. Evaluating / Planning - We are reviewing the administrative features of cloud providers. We are drafting policies for who is allowed to run jobs on real hardware vs. simulators. | CG7: 1 | CI7: 2. Evaluating / Planning - We read the public roadmaps (e.g., "IBM Quantum Development Roadmap"). We are aware of the milestones but do not explicitly link our internal project deadlines to them. | CJ7: 1 | CL7: 2. Evaluating / Planning - We are discussing how to merge the teams. We invite quantum researchers to general R&D town halls, but they still have separate budgets and reporting lines. | CM7: 1 | CO7: 2. Evaluating / Planning - Business leaders attend the occasional demo. They express interest ("Keep us posted"), but they do not contribute budget or resources. | CP7: 1 | CR7: 2. Evaluating / Planning - We are discussing the need for a CoE. We are identifying which experts should belong to it, but currently, they sit in isolated silos (e.g., IT vs. R&D). | CS7: 1 | CU7: 2. Evaluating / Planning - We have "Ad-Hoc" funding. We have to pitch for money for every single pilot. We spend more time writing grant proposals to the CFO than writing code. | CV7: 1 | CX7: 2. Evaluating / Planning - We are writing job descriptions. We are debating whether to hire a senior physicist or a fresh PhD. We have not made an offer yet. | CY7: 1 | DA7: 2. Evaluating / Planning - We are reviewing our IP policies. We want to allow some publishing, but Legal is currently blocking it due to fear of accidental disclosure. | DB7: 1 | DD7: 2. Evaluating / Planning - We talk about Failing Fast, but our HR policies don't support it. Managers verbally encourage risk, but performance reviews still penalize missed targets regardless of the cause. | DE7: 1 | DG7: 2. Evaluating / Planning - We discuss risk in the abstract. The Board nods when we say "Quantum is long-term," but when earnings are tight, the quantum budget is the first to be cut. | DH7: 1 | DJ7: 2. Evaluating / Planning - We do Ad-Hoc experimentation. If an engineer has a cool idea, they try to build it. There is no standard criteria for what is worth building. Success is random. | DK7: 1 | DM7: 2. Evaluating / Planning - Quantum is listed in the Emerging Technology appendix of our strategy. It is flagged as something to watch, but no specific scenarios or financial impacts are modeled. | DN7: 1 | DP7: 2. Evaluating / Planning - We have "Qualitative" goals. We use vague terms like "disruption," "acceleration," or "future-proofing," but we have not put a dollar figure on the outcome. | DQ7: 1 | DS7: 2. Evaluating / Planning - We are drafting a "Quantum QA" checklist. We are determining what the acceptance criteria should be (e.g., minimum fidelity scores, maximum latency), but have not enforced them yet. | DT7: 1 | DV7: 2. Evaluating / Planning - We use Kanban boards (e.g., Trello) to track tasks, but we don't have time-boxed sprints. Deadlines are flexible and often slide by weeks. | DW7: 1 | DY7: 2. Evaluating / Planning - We are evaluating Quantum-Inspired algorithms (running tensor networks on GPUs). We see the potential for intermediate value, but haven't deployed anything. | DZ7: 1 | EB7: 2. Evaluating / Planning - We review our code when a vendor makes a Major Announcement (e.g., a new 1,000-qubit chip). We have no regular schedule for optimization; it happens only when we read a press release. | EC7: 1 | EE7: 2. Evaluating / Planning - We are reviewing Quantum-Safe protocols. We are aware of the NIST PQC standards but have not implemented them in our development environment yet. | EF7: 1
C8: 3. Experimenting / In Progress - We have a formal project underway to identify use cases. We are actively assessing specific pain points against quantum modalities. | D8: 1.5 | F8: 3. Experimenting / In Progress - We are developing an internal model to map technical milestones (e.g., error correction rates) to our specific business timeline. | G8: 1.5 | I8: 3. Experimenting / In Progress - We have assigned a team member or subscribed to a service to collect market data. We are beginning to filter specific signals relevant to our industry. | J8: 1.5 | L8: 3. Experimenting / In Progress - We are actively meeting with startups and running limited trials. We are trying to validate their technical claims against our needs. | M8: 1.5 | O8: 3. Experimenting / In Progress - We have a "scouting list." Corporate Development is aware of the quantum landscape and has identified potential targets or teams for "acqui-hire." | P8: 1.5 | R8: 3. Experimenting / In Progress - We are actively testing problems. We are running "benchmarks" to see if a quantum solver (e.g., QAOA) performs differently than our classical heuristics. | S8: 1.5 | U8: 3. Experimenting / In Progress - We have drafted preliminary timelines for specific pilots. We know when the PoC ends, but not necessarily when production value begins. | V8: 1.5 | X8: 3. Experimenting / In Progress - We have established basic oversight for individual pilots. Project managers track progress, but there is no enterprise-wide standard for "success." | Y8: 1.5 | AA8: 3. Experimenting / In Progress - We are deploying "Quantum-Inspired" solutions (e.g., tensor networks on GPUs) to solve problems today. We are cleaning data specifically for future quantum ingestion. | AB8: 1.5 | AD8: 3. Experimenting / In Progress - We are running a single-track experiment (e.g., only Optimization). We are "all-in" on one domain and ignoring others. | AE8: 1.5 | AG8: 3. Experimenting / In Progress - We have successfully negotiated "Foreground IP" ownership for specific pilots. We treat IP on a case-by-case basis. | AH8: 1.5 | AJ8: 3. Experimenting / In Progress - We make decisions on a case-by-case basis. We have an IP review committee, but the criteria for "Patent vs. Secret" are subjective and inconsistent. | AK8: 1.5 | AM8: 3. Experimenting / In Progress - We have an "Invention Disclosure Form" (IDF) process. Reviews happen sporadically when enough forms accumulate. Assessment is mostly technical, lacking business context. | AN8: 1.5 | AP8: 3. Experimenting / In Progress - We have filed 1-2 provisional patents based on initial pilots. Filings are sporadic and driven by individual researcher initiative rather than corporate strategy. | AQ8: 1.5 | AS8: 3. Experimenting / In Progress - We have drafted licensing terms for a specific pilot. We might be sharing a solution with a close supply chain partner, but the commercial terms are undefined. | AT8: 1.5 | AV8: 3. Experimenting / In Progress - We have mentioned quantum simulation methods in preliminary discussions with a regulator for a specific pilot. We are testing their appetite for non-classical data. | AW8: 1.5 | AY8: 3. Experimenting / In Progress - We are conducting a "Gap Analysis." We are testing if our current pilots can be ported to a standard format (e.g., OpenQASM) or if they break. | AZ8: 1.5 | BB8: 3. Experimenting / In Progress - We are a paying member of a consortium. We attend the annual conference and receive the newsletters. Our engagement is passive consumption of information. | BC8: 1.5 | BE8: 3. Experimenting / In Progress - We have containerized specific pilots. We are testing if we can package a quantum circuit and its classical pre-processing into a single deployable unit. | BF8: 1.5 | BH8: 3. Experimenting / In Progress - We have scripted a basic loop. A Python script sends a job to the cloud QPU, waits for the result, and processes it. Latency is high due to queue times and network lag. | BI8: 1.5 | BK8: 3. Experimenting / In Progress - We use basic transpilation tools (e.g., Qiskit levels 1-3) to map circuits to the hardware topology. We are manually trying to reduce gate counts. | BL8: 1.5 | BN8: 3. Experimenting / In Progress - We have built custom scripts to bridge the gap. We export quantum results to a CSV or JSON file and manually load them into a visualization tool for the business to see. | BO8: 1.5 | BQ8: 3. Experimenting / In Progress - We are training small hybrid models. We use classical neural networks for the bulk of the work and a small quantum circuit for specific tasks (like classification of complex correlations). | BR8: 1.5 | BT8: 3. Experimenting / In Progress - We are running "Toy Models." We have replaced a small section of a classical simulation with a quantum circuit. It is currently slower and less accurate, but it proves the connection works. | BU8: 1.5 | BW8: 3. Experimenting / In Progress - We are testing "Feature Maps." We are taking small datasets and experimenting with how to encode them into qubits (e.g., Angle Encoding vs. Amplitude Encoding). | BX8: 1.5 | BZ8: 3. Experimenting / In Progress - We have active accounts on one platform (e.g., IBM or AWS). We are running pilots using "Free Tier" or ad-hoc credits. Access is manual and dependent on individual developers. | CA8: 1.5 | CC8: 3. Experimenting / In Progress - We have a basic CI pipeline. It runs automated tests on classical simulators whenever code is committed. It does not yet test against real hardware. | CD8: 1.5 | CF8: 3. Experimenting / In Progress - We have a single administrator who manually manages access keys and tracks usage via spreadsheets. Reporting is retroactive (at the end of the month). | CG8: 1.5 | CI8: 3. Experimenting / In Progress - We have loose alignment. We try to target our pilots to current hardware capabilities. We adjust our expectations when vendors announce delays. | CJ8: 1.5 | CL8: 3. Experimenting / In Progress - We have "Liaison Officers." A few R&D engineers are assigned to rotate through the quantum team to learn the capability. Information flows, but structural silos remain. | CM8: 1.5 | CO8: 3. Experimenting / In Progress - We have a "Business Sponsor" for our pilots. They lend their name to the project to help secure funding, but they do not have specific deliverables. | CP8: 1.5 | CR8: 3. Experimenting / In Progress - We have a "Virtual CoE" or Community of Interest. It’s a Slack channel or a monthly lunch-and-learn where enthusiasts share tips. It has no budget or authority. | CS8: 1.5 | CU8: 3. Experimenting / In Progress - We have Project-Based funding. We got $500k for this specific pilot. If it fails, the money stops. We are terrified of taking risks because we need a win to survive. | CV8: 1.5 | CX8: 3. Experimenting / In Progress - We have hired 1-2 Physicists. They are brilliant but isolated. They struggle to integrate their code into our corporate IT stack because they lack software engineering skills. | CY8: 1.5 | DA8: 3. Experimenting / In Progress - We allow Passive participation. Staff can attend conferences and fix minor bugs in public libraries, but they cannot release significant code or act as maintainers. | DB8: 1.5 | DD8: 3. Experimenting / In Progress - We allow failure in The Lab. The R&D team has a safe space to fail, but they must sanitize their reports before presenting to the Board to look successful. | DE8: 1.5 | DG8: 3. Experimenting / In Progress - We have Hedged bets. We invest small amounts across many technologies. We accept some failure, but we constantly demand intermediate milestones that may not be scientifically valid just to prove progress. | DH8: 1.5 | DJ8: 3. Experimenting / In Progress - We are stuck in PoC Purgatory. We can successfully build a Proof of Concept (PoC), but we have no mechanism to graduate it to production. We have a graveyard of successful pilots that never scaled. | DK8: 1.5 | DM8: 3. Experimenting / In Progress - We have a specific "Quantum Roadmap" within the IT/R&D division, but it is disconnected from the broader corporate strategy. The CEO's master plan does not rely on quantum success. | DN8: 1.5 | DP8: 3. Experimenting / In Progress - We calculate value after the fact. We finish a pilot and then try to back-calculate what it might be worth if scaled. We are rationalizing the spend rather than justifying the investment. | DQ8: 1.5 | DS8: 3. Experimenting / In Progress - We certify based on "Simulator Success." If the code runs correctly on a perfect classical simulator, we approve it. We do not rigorously validate against the noise profiles of real hardware. | DT8: 1.5 | DV8: 3. Experimenting / In Progress - We try to run 2-week sprints, but we constantly miss our goals because Physics is unpredictable. The team is frustrated by the mismatch between rigid Scrum and messy science. | DW8: 1.5 | DY8: 3. Experimenting / In Progress - We deploy "Hybrid Proofs." We run small parts of a problem on a quantum backend to show it works, but for production, we revert to the classical solver because it's still cheaper/faster. | DZ8: 1.5 | EB8: 3. Experimenting / In Progress - We perform Manual Refactoring. Every quarter, our physicists manually review the codebase to see if they can optimize the circuits for the current noise environment. It is effective but labor-intensive. | EC8: 1.5 | EE8: 3. Experimenting / In Progress - We apply "Basic Hygiene." We use standard TLS for data transmission and rotate API keys. However, our quantum code itself is not scanned for vulnerabilities or logic flaws. | EF8: 1.5
C9: 4. Mostly Complete - We have a comprehensive map of opportunities defined. We have identified high-priority use cases, though final validation or enterprise-wide coverage is pending. | D9: 2 | F9: 4. Mostly Complete - We have a solid forecast for our key sectors. The model exists and informs strategy, but it may lack real-time updates or full executive buy-in | G9: 2 | I9: 4. Mostly Complete - We have a structured monitoring process. We track key indices (investment, hardware specs, patents) and distribute regular updates to stakeholders. | J9: 2 | L9: 4. Mostly Complete - We have a qualified vendor matrix. We know exactly which startups map to our specific problem classes (e.g., QuEra for simulation, Classiq for software). | M9: 2 | O9: 4. Mostly Complete - We have a vetted pipeline. We have engaged with specific targets. We have models valuing their IP and talent against our strategic roadmap. | P9: 2 | R9: 4. Mostly Complete - We have identified specific "intractable" problems where classical methods fail. We have a shortlist of use cases where quantum shows a theoretical path to advantage. | S9: 2 | U9: 4. Mostly Complete - We have a detailed roadmap linking technical milestones (e.g., "100 logical qubits") to specific business value triggers (e.g., "Optimize logistics fleet by 5%"). | V9: 2 | X9: 4. Mostly Complete - We have a defined governance handbook. We have clear stages (Ideation -> PoC -> Pilot) and criteria for moving between them. | Y9: 2 | AA9: 4. Mostly Complete - We have broad deployment of no-regret assets. Our workforce is upskilled in quantum concepts (linear algebra), and our data pipelines are modernized. | AB9: 2 | AD9: 4. Mostly Complete - We have a diversified portfolio. We are testing across at least two domains (e.g., Simulation + Optimization) as recommended by QRO data. | AE9: 2 | AG9: 4. Mostly Complete - We have a standardized Quantum IP Addendum for all vendors. It explicitly defines "Background IP" (theirs) vs. "Foreground IP" (ours). | AH9: 2 | AJ9: 4. Mostly Complete - We have a formal decision tree. It weighs factors like "detectability" (can we prove infringement?) and "reverse engineering risk" to guide the protection strategy. | AK9: 2 | AM9: 4. Mostly Complete - We have a formal Invention Review Board (IRB) that meets quarterly. It includes legal and technical experts. We evaluate disclosures against prior art and business relevance. | AN9: 2 | AP9: 4. Mostly Complete - We have a targeted filing roadmap. We are systematically filing on specific "choke points" in our workflow (e.g., the data encoding layer). We have a growing portfolio. | AQ9: 2 | AS9: 4. Mostly Complete - We have a formal licensing framework. We have standard terms for "Out-Licensing" our technology. We have identified potential licensees (suppliers, non-competing industries). | AT9: 2 | AV9: 4. Mostly Complete - We have a formal working group engaging agencies. We are drafting white papers on how to validate quantum-designed materials to satisfy safety standards (e.g., ISO 26262). | AW9: 2 | AY9: 4. Mostly Complete - We require standards compliance in our procurement. We will not sign a vendor contract unless they support open standards (e.g., QED-C benchmarks). We have started PQC migration. | AZ9: 2 | BB9: 4. Mostly Complete - We actively participate in Working Groups (e.g., "Use Case Definition" or "Workforce Development"). We contribute data and help draft industry white papers. | BC9: 2 | BE9: 4. Mostly Complete - Standard operating procedure is to containerize all quantum code. We can deploy workloads to the cloud reliably. However, switching vendors still requires manual tweaks to the container. | BF9: 2 | BH9: 4. Mostly Complete - We use a runtime environment where the classical code runs next to the quantum processor (co-located). The handoff is automated and low-latency. | BI9: 2 | BK9: 4. Mostly Complete - We use "Sessions" or "Batch Mode" execution. We group our jobs to reserve a dedicated block of time on the machine, eliminating the queue for iterative algorithms. | BL9: 2 | BN9: 4. Mostly Complete - We have automated data pipelines. The quantum job triggers automatically based on a business event (e.g., "Nightly Inventory Update"), and the results are pushed back to a shared database. | BO9: 2 | BQ9: 4. Mostly Complete - We use AI to optimize our quantum hardware. We employ classical Machine Learning to suppress quantum errors (Error Mitigation), allowing us to run longer circuits than otherwise possible. | BR9: 2 | BT9: 4. Mostly Complete - We have integrated quantum calls into our HPC schedulers (e.g., Slurm, Kubernetes). Our supercomputing clusters can dispatch jobs to a quantum backend as easily as to a GPU. | BU9: 2 | BW9: 4. Mostly Complete - Our data is API-accessible and "Schema-Strict." We have automated pipelines that clean and normalize data specifically for high-performance computing ingestion. | BX9: 2 | BZ9: 4. Mostly Complete - We have enterprise-grade access. We utilize "Reserved Instances" or dedicated access to ensure our jobs run without waiting in public queues. We have central billing and security controls. | CA9: 2 | CC9: 4. Mostly Complete - We have a robust pipeline. We run regression tests against simulators and small-scale quantum hardware. We catch breaking changes in vendor SDKs automatically. | CD9: 2 | CF9: 4. Mostly Complete - We use automated administration tools integrated with corporate SSO (Single Sign-On). We have set strict "hard limits" on usage quotas per department. | CG9: 2 | CI9: 4. Mostly Complete - We have a "Coupled Roadmap." Our 3-year plan explicitly states: "In Q3 2026, when Vendor X releases 10k gates, we deploy Module Y." We have contingency plans for hardware slippage. | CJ9: 2 | CL9: 4. Mostly Complete - We have "Matrix Integration." Quantum projects are sponsored by specific R&D Business Lines (e.g., the Battery Division pays for the Battery Simulation pilot). The quantum lead reports to the R&D CTO. | CM9: 2 | CO9: 4. Mostly Complete - We have "Dual Sign-Off." The CIO and the Business Unit Leader must both approve the roadmap. The Business Unit contributes a portion of the funding. | CP9: 2 | CR9: 4. Mostly Complete - We have a formal, funded CoE. It has a dedicated lead and budget. It publishes the Standard Operating Procedures (SOPs) for quantum coding and vetting vendors. | CS9: 2 | CU9: 4. Mostly Complete - We have a Ring-Fenced Annual Budget. We have a dedicated line item for Emerging Tech that is protected from standard efficiency cuts. We can fail on individual experiments without losing the program. | CV9: 2 | CX9: 4. Mostly Complete - We have a Two-Legged Stool. We have Physicists and Software Engineers working together. The code is robust. The missing piece is the Translator, someone who can explain why this matters to the CEO. | CY9: 2 | DA9: 4. Mostly Complete - We are Active Contributors. We have a formal approval process that allows staff to publish non-sensitive research. We encourage PRs (Pull Requests) to major frameworks like Qiskit or Pennylane. | DB9: 2 | DD9: 4. Mostly Complete - We practice "Blameless Post-Mortems." When an experiment fails, we analyze the process, not the person. We view a negative result (e.g., "This molecule doesn't bind") as a successful outcome because it saves us from wasting further money. | DE9: 2 | DG9: 4. Mostly Complete - We have a Strategic Risk Framework. The Board has signed off on a 3-year Zero Revenue period for Quantum. We view the risk as "Asymmetric", the cost of doing nothing is higher than the cost of failing. | DH9: 2 | DJ9: 4. Mostly Complete - We have a Stage-Gate Process. We have formal review gates (Idea -> Feasibility -> Pilot -> Production). We kill bad ideas early and resource good ideas for integration. | DK9: 2 | DM9: 4. Mostly Complete - We use Scenario Planning. Our corporate strategy includes Quantum Accelerate and Quantum Stagnate scenarios. We have modeled how a breakthrough in 2027 would alter our supply chain and competitive positioning. | DN9: 2 | DP9: 4. Mostly Complete - We require a "Value Hypothesis" before approval. The project charter must state: "A 1% improvement in this algorithm saves $5M in logistics costs annually." We reject projects that lack this clarity. | DQ9: 2 | DS9: 4. Mostly Complete - We have a "Robustness Standard." To be certified for production, a solution must pass a "Noise Resilience Test." It must prove it can maintain accuracy even when error rates spike by 10%. | DT9: 2 | DV9: 4. Mostly Complete - We use "Dual-Track Agile." The Software Engineering team runs standard 2-week sprints. The Physics team runs longer, variable "Research Cycles." They sync up every month to integrate. | DW9: 2 | DY9: 4. Mostly Complete - We utilize "Heuristic Advantages." We deploy solutions that use quantum (or quantum-inspired) solvers to break out of local minima, even if the final optimization is classical. We capture small wins (1-2% efficiency gains). | DZ9: 2 | EB9: 4. Mostly Complete - We have Scheduled Optimization Cycles. Our CI/CD pipeline includes a Re-Transpilation step. We verify that our circuits are using the latest native gate sets (e.g., Dynamic Circuits) supported by the backend. | EC9: 2 | EE9: 4. Mostly Complete - We have "Obfuscated Execution." We use circuit knitting or data masking techniques to ensure that the quantum cloud provider never sees the full problem. We treat the quantum backend as an "Untrusted Environment." | EF9: 2
C10: 5. Fully Complete - We have a fully institutionalized, continuous process for identifying and validating quantum opportunities. The mapping is dynamic, covering the entire enterprise and aligned with strategy. | D10: 2.5 | F10: 5. Fully Complete - We maintain a dynamic, living scenario model. It is integrated into corporate strategy, updated quarterly based on hardware metrics, and drives immediate capital allocation decisions. | G10: 2.5 | I10: 5. Fully Complete - We have a comprehensive, curated intelligence engine. Market data triggers immediate strategic reviews. We track deep technical metrics (not just news) and competitor IP filings in near real-time. | J10: 2.5 | L10: 5. Fully Complete - We have a continuous, deep-dive vetting process. We audit their technical stack and their solvency. We view them as strategic partners, integrating their specific "value add" into our long-term roadmap. | M10: 2.5 | O10: 5. Fully Complete - We have an active, funded acquisition engine. We regularly close strategic investments or partnerships that lock in exclusive access to talent and IP. Integration playbooks are ready. | P10: 2.5 | R10: 5. Fully Complete - We have a rigorous "Go/No-Go" framework. We only deploy quantum resources when we can mathematically prove a path to advantage in accuracy, cost, or efficiency. We do not waste qubits on classical problems. | S10: 2.5 | U10: 5. Fully Complete - We have a dynamic ROI model integrated into our 5-year financial plan. We have defined "break-even" dates for each use case and adjust capital allocation quarterly based on acceleration or delays in the technology. | V10: 2.5 | X10: 5. Fully Complete - We have a rigorous, automated "Stage-Gate" mechanism integrated into corporate R&D. We have a "Kill Switch" that ruthlessly deprioritizes projects missing their KPIs, reallocating capital instantly. | Y10: 2.5 | AA10: 5. Fully Complete - We have institutionalized these capabilities. Our "Quantum" program is self-funding because it generates current P&L efficiency through better classical heuristics and data structures. | AB10: 2.5 | AD10: 5. Fully Complete - We have a mature, multi-track exploration engine. We have validated feasibility in multiple domains and are now "Integrating" the winners into production while cutting the losers. | AE10: 2.5 | AG10: 5. Fully Complete - We have an impenetrable "IP Fortress." We not only own the IP; we have a strategy to effectively hide it (Trade Secrets) or fence it (Patents). We audit vendor compliance to ensure no leakage of our data or algorithms into their public models. | AH10: 2.5 | AJ10: 5. Fully Complete - We have an institutionalized, strategic decision engine. The model is integrated with our "HNDL" defense strategy. We deliberately use Open Source to commoditize layers where we don't differentiate, and Trade Secrets to lock down the "Crown Jewels." | AK10: 2.5 | AM10: 5. Fully Complete - We have a proactive "IP Mining" engine. We embed IP strategists into R&D sprints to identify inventions as they happen. The Review Board grades every concept on a "Commercial Impact" matrix before spending a dime on legal fees. | AN10: 2.5 | AP10: 5. Fully Complete - We are building a "Patent Thicket." We file offensive and defensive patents surrounding our core use cases. We deliberately create a "minefield" that forces competitors to cross-license with us to operate in our sector. | AQ10: 2.5 | AS10: 5. Fully Complete - We have an active, revenue-generating licensing engine. Our suppliers pay us to use our quantum-optimized logistics tools. We use cross-licensing to access competitor IP without cash outlay. | AT10: 2.5 | AV10: 5. Fully Complete - We are a "Reference Architecture" partner. We are co-authoring the validation standards with the agency. Our validation protocols are becoming the industry requirement, effectively creating a regulatory moat against competitors who can't meet our standard. | AW10: 2.5 | AY10: 5. Fully Complete - We have achieved "Universal Interoperability." Our entire stack is built on open standards. We can swap backend providers (e.g., IBM to Pasqal) with zero code rewrites because our "Understanding" has translated into a perfectly modular architecture. | AZ10: 2.5 | BB10: 5. Fully Complete - We hold leadership positions (Board/Chair) in key industry bodies. We steer the agenda to favor our specific technical needs (e.g., "Standardizing Neutral Atom benchmarks"). We use the ecosystem to build our supply chain. | BC10: 2.5 | BE10: 5. Fully Complete - We have achieved "Sovereign Code." Our containers are fully abstracted. We can take a workload running on Vendor A, change a config line, and redeploy it to Vendor B's container service without breaking the build. | BF10: 2.5 | BH10: 5. Fully Complete - We have "Intelligent Orchestration." Our workload manager dynamically assigns tasks. If the QPU is busy or error-prone, it falls back to a classical simulator automatically. The user doesn't even know which machine solved the problem. | BI10: 2.5 | BK10: 5. Fully Complete - We have "Dynamic Optimization." Our stack automatically rewrites circuits in real-time based on the daily calibration data of the specific chip we are targeting. We use advanced error suppression to get accurate results with fewer "shots," directly reducing cost and time. | BL10: 2.5 | BN10: 5. Fully Complete - We have "Seamless Ingestion." The quantum solver is wrapped as a standard API. The downstream user (e.g., a factory scheduler) interacts with their normal dashboard, unaware that the optimization suggestion came from a QPU. | BO10: 2.5 | BQ10: 5. Fully Complete - We have a "Convergent Stack." Our workflow automatically selects the best accelerator. It uses Quantum for feature space expansion and Classical AI for pattern recognition. The interplay is seamless and automated. | BR10: 2.5 | BT10: 5. Fully Complete - We have "Workflow Sovereignty." We seamlessly mix CPU, GPU, and QPU resources. We use "Quantum-Centric Supercomputing" to solve problems that were previously impossible, effectively extending the boundaries of our computational science. | BU10: 2.5 | BW10: 5. Fully Complete - We have "Quantum-Ready Data." We prioritize "High-Dimensional" data richness. We have pre-calculated classical features to minimize the "State Preparation" cost on the quantum hardware. | BX10: 2.5 | BZ10: 5. Fully Complete - We have a "Multi-Cloud Agnostic" strategy. We use an abstraction layer that allows us to route a job to any backend (IonQ, Rigetti, IBM) based on availability, fidelity, or cost. We are not beholden to any single provider. | CA10: 2.5 | CC10: 5. Fully Complete - We have "Calibration-Aware" CI/CD. Our pipeline pulls the daily calibration data (noise profiles) from the hardware provider before the build. It automatically re-transpiles and optimizes the circuit for today's hardware reality. | CD10: 2.5 | CF10: 5. Fully Complete - We have implemented Quantum FinOps. Our administration tools provide real-time cost anomaly detection. We dynamically reallocate unused quotas between teams. We have automated "chargeback" models that bill the specific business unit (e.g., Logistics) for their quantum consumption. | CG10: 2.5 | CI10: 5. Fully Complete - We have "Co-Development" status. We meet with vendor product teams under NDA to see the real roadmap (not the public marketing one). We influence their feature set to prioritize the gates/connectivity we need. | CJ10: 2.5 | CL10: 5. Fully Complete - We have "Unified R&D." Quantum is just another tool in the R&D toolbox, alongside AI and HPC. We have mixed squads of physicists, chemists, and software engineers working on the same Jira ticket. The distinction between "Quantum Team" and "R&D Team" has vanished. | CM10: 2.5 | CO10: 5. Fully Complete - We have Shared P&L Accountability. Quantum Readiness is a formal KPI on both executives' annual reviews. If the project fails to deliver ROI, both lose their bonus. | CP10: 2.5 | CR10: 5. Fully Complete - We have a Federated Hub-and-Spoke model. The Central CoE sets the standards, but Quantum Champions are embedded in every business unit (Logistics, Finance, Chem). The CoE functions as an internal "University" and "Consultancy." | CS10: 2.5 | CU10: 5. Fully Complete - We have a Venture Capital Model. We fund the portfolio, not the project. We allocate 'Horizon 3' capital that expects zero ROI for 3 years. We release funds in tranches based on learning milestones, not just profit milestones. | CV10: 2.5 | CX10: 5. Fully Complete - We have the Golden Triangle. Our squad includes a Physicist (Science), a DevOps Engineer (Scale), and a Business Translator (Value). They operate as a single unit. | CY10: 2.5 | DA10: 5. Fully Complete - We are Ecosystem Leaders. We maintain our own open-source tools that others use. Our staff hold chair positions in technical committees. We view our open-source presence as our primary recruiting funnel. | DB10: 2.5 | DD10: 5. Fully Complete - We celebrate Invalidated Hypotheses. We literally throw a party when a team kills a project early based on data. We view Negative Knowledge (knowing what doesn't work) as a proprietary asset that keeps us ahead of competitors who are still trying it. | DE10: 2.5 | DG10: 5. Fully Complete - We have a Venture Risk Profile. We expect 90% of our quantum projects to fail. We optimize for Magnitude of Success, not Frequency of Success. We are willing to lose $10M to find the one $1B opportunity. | DH10: 2.5 | DJ10: 5. Fully Complete - We have an Innovation Factory. Our funnel is automated. Validated quantum algorithms are automatically wrapped in APIs and pushed to the CI/CD pipeline. The time from "Whiteboard" to "Live Service" is measured in weeks, not years. | DK10: 2.5 | DM10: 5. Fully Complete - Quantum is a Strategic Pillar. Our long-term corporate goals (e.g., Carbon Neutral by 2035) are explicitly dependent on quantum breakthroughs. We have bet the farm that this technology will unlock the efficiencies we need to hit our targets. | DN10: 2.5 | DP10: 5. Fully Complete - We benchmark against "Classical Best." Our value calculation explicitly subtracts the cost of the classical alternative. We only pursue quantum if the net value (Quantum Value minus Classical Cost) is positive and significant. | DQ10: 2.5 | DS10: 5. Fully Complete - We use Verification & Validation (V&V) Protocols. We use formal methods (and sometimes classical supercomputers) to mathematically prove the bounds of the quantum answer. We issue a Certificate of Correctness with every run. | DT10: 2.5 | DV10: 5. Fully Complete - We practice "Hypothesis-Driven Development." Every sprint ends with a concrete experimental result (even if it's negative). We pivot our roadmap every 2 weeks based on what the quantum computer actually did, not what we hoped it would do. | DW10: 2.5 | DY10: 5. Fully Complete - We have a Sliding Scale Architecture. Our software automatically detects the hardware capability. Today it runs 99% classical / 1% quantum. As qubits improve, it automatically shifts to 50% / 50%. We release value continuously without re-platforming. | DZ10: 2.5 | EB10: 5. Fully Complete - We use Adaptive Compilation. Our software stack automatically profiles the specific quantum processor at runtime. If the chip has a new connectivity map or lower error rate on Qubit 4, the compiler rewrites the circuit on the fly to exploit it. | EC10: 2.5 | EE10: 5. Fully Complete - We have a Crypto-Agile Pipeline. Our CI/CD pipeline automatically signs every quantum job with Post-Quantum Cryptography (PQC). If a new vulnerability is found in a PQC algorithm, we can swap it out globally in minutes. | EF10: 2.5
